test/__init__.py
test/test_colon_rules.py
test/test_dash_rules.py
test/test_filter.py
test/test_purify.py
test/test_quote_rules.py
test/test_range_rules.py
test/test_time_rules.py
test/test_wordcounter.py
wlint/__init__.py
wlint/count_words.py
wlint/driver.py
wlint/filter.py
wlint/list_filter.py
wlint/plugin.py
wlint/punctuation_style.py
wlint/purify.py
wlint/tool.py
wlint/wordcounter.py
wlint/punctuation/__init__.py
wlint/punctuation/colon.py
wlint/punctuation/dash.py
wlint/punctuation/quote.py
wlint/punctuation/range.py
wlint/punctuation/time.py
wlint/share/filter-lists/filter-words.txt
wlint/share/filter-lists/thought-words.txt
wlint/share/filter-lists/weasel-words.txt
wlint-0.1.0a0.dist-info/DESCRIPTION.rst
wlint-0.1.0a0.dist-info/METADATA
wlint-0.1.0a0.dist-info/RECORD
wlint-0.1.0a0.dist-info/WHEEL
wlint-0.1.0a0.dist-info/entry_points.txt
wlint-0.1.0a0.dist-info/metadata.json
wlint-0.1.0a0.dist-info/top_level.txt
