Metadata-Version: 2.0
Name: wlint
Version: 0.1.0a0
Summary: Linter tools for writing
Home-page: https://github.com/snewell/wlint
Author: Stephen Newell
Author-email: UNKNOWN
License: BSD-2
Platform: UNKNOWN
Classifier: Development Status :: 2 - Pre-Alpha
Classifier: Environment :: Console
Classifier: License :: OSI Approved :: BSD License
Classifier: Topic :: Utilities
